<?xml version="1.0" encoding="UTF-8"?>
<openerp>
    <data>
        <record id='motivo_1' model='chatarra.motivo'>
        	<field name='name'>PLACA NO EXISTE</field>
        </record>
        <record id='motivo_2' model='chatarra.motivo'>
        	<field name='name'>PLACA CANCELADA</field>
        </record>
        <record id='motivo_3' model='chatarra.motivo'>
        	<field name='name'>PLACA DADA DE BAJA</field>
        </record>
        <record id='motivo_4' model='chatarra.motivo'>
        	<field name='name'>FECHA DE ALTA</field>
        </record>
        <record id='motivo_5' model='chatarra.motivo'>
        	<field name='name'>EN REVISION</field>
        </record>
        <record id='motivo_6' model='chatarra.motivo'>
        	<field name='name'>PLACA DUPLICADA</field>
        </record>
        <record id='motivo_7' model='chatarra.motivo'>
        	<field name='name'>REASIGNA A OTRO CLIENTE</field>
        </record>
        <record id='motivo_8' model='chatarra.motivo'>
        	<field name='name'>NO PASO SCT</field>
        </record>
        <record id='motivo_9' model='chatarra.motivo'>
        	<field name='name'>DESTRUIDA</field>
        </record>
        <record id='motivo_10' model='chatarra.motivo'>
        	<field name='name'>SE ENCUENTRA BLOQUEADA</field>
        </record>
        <record id='motivo_11' model='chatarra.motivo'>
        	<field name='name'>PESO EN CEROS</field>
        </record>
        <record id='motivo_12' model='chatarra.motivo'>
        	<field name='name'>NUMERO DE SERIE ERRONEO</field>
        </record>
        <record id='motivo_13' model='chatarra.motivo'>
        	<field name='name'>NUMERO DE MOTOR ERRONEO</field>
        </record>
        <record id='motivo_14' model='chatarra.motivo'>
        	<field name='name'>MARCA ERRONEA</field>
        </record>
        <record id='motivo_15' model='chatarra.motivo'>
        	<field name='name'>MOVIMIENTO RESIENTE</field>
        </record>
        <record id='motivo_16' model='chatarra.motivo'>
        	<field name='name'>PROPIETARIO ANTERIOR ES CLIENTE</field>
        </record>
        <record id='motivo_17' model='chatarra.motivo'>
        	<field name='name'>MATERIALES PELIGROSOS</field>
        </record>
        <record id='motivo_18' model='chatarra.motivo'>
        	<field name='name'>NO CUMPLE CON EL DECRETO</field>
        </record>
        <record id='motivo_19' model='chatarra.motivo'>
        	<field name='name'>DISCREPANCIA EN MARCA</field>
        </record>
        <record id='motivo_20' model='chatarra.motivo'>
        	<field name='name'>RFC NO CORRESPONDE</field>
        </record>
        <record id='motivo_21' model='chatarra.motivo'>
        	<field name='name'>EMPROBLEMADA</field>
        </record>
        <record id='motivo_22' model='chatarra.motivo'>
        	<field name='name'>BAJA POR CANJE</field>
        </record>
        <record id='motivo_23' model='chatarra.motivo'>
        	<field name='name'>FALTA MIGRAR</field>
        </record>
        <record id='motivo_24' model='chatarra.motivo'>
        	<field name='name'>MODELO RESIENTE</field>
        </record>
        <record id='motivo_25' model='chatarra.motivo'>
        	<field name='name'>NO SE PUEDE MIGRAR</field>
        </record>
        <record id='motivo_26' model='chatarra.motivo'>
        	<field name='name'>PROPIETARIO ANTERIOR HARA MOVIMIENTO</field>
        </record>
        <record id='motivo_27' model='chatarra.motivo'>
        	<field name='name'>NO ESTA DADA DE ALTA</field>
        </record>
        <record id='motivo_28' model='chatarra.motivo'>
        	<field name='name'>ERROR EN SCT</field>
        </record>
        <record id='motivo_29' model='chatarra.motivo'>
        	<field name='name'>CAMION YA EXISTE PERO CON DIFERENTE PLACA</field>
        </record>
    </data>
</openerp>